django_query_utils/__init__.py
django_query_utils-0.0.5.dist-info/LICENSE
django_query_utils-0.0.5.dist-info/METADATA
django_query_utils-0.0.5.dist-info/WHEEL
django_query_utils-0.0.5.dist-info/top_level.txt
django_query_utils-0.0.5.dist-info/RECORD
