Metadata-Version: 2.1
Name: django-query-utils
Version: 0.0.5
Summary: Handful utils to work with raw queries in Django
Home-page: https://github.com/surenkov/django-query-utils
Author: Savva Surenkov
Author-email: savva@surenkov.space
Keywords: django,sql,postgres,query
Classifier: Development Status :: 4 - Beta
Classifier: Intended Audience :: Developers
Classifier: Framework :: Django
Classifier: License :: OSI Approved :: MIT License
Classifier: Programming Language :: Python :: 3
Requires-Python: >=3.8
License-File: LICENSE
Requires-Dist: django (>=3.0)
Provides-Extra: dev
Requires-Dist: black ; extra == 'dev'
Requires-Dist: mypy (==0.961) ; extra == 'dev'
Requires-Dist: flake8 (==4.0.*) ; extra == 'dev'
Requires-Dist: pytest (==7.0.*) ; extra == 'dev'
Requires-Dist: pytest-reraise (==2.1.*) ; extra == 'dev'
Requires-Dist: django-stubs[compatible-mypy] ; extra == 'dev'
Requires-Dist: pytest-django (<5,>=4.5) ; extra == 'dev'
Provides-Extra: filters
Requires-Dist: django-query-utils[postgres] ; extra == 'filters'
Requires-Dist: django-filter (>=2.0) ; extra == 'filters'
Provides-Extra: postgres
Requires-Dist: psycopg2-binary (<3,>=2.7) ; extra == 'postgres'
